ocf_ml_metrics/__init__.py
ocf_ml_metrics/baselines/__init__.py
ocf_ml_metrics/baselines/intraday.py
ocf_ml_metrics/baselines/simple.py
ocf_ml_metrics/evaluation/__init__.py
ocf_ml_metrics/evaluation/evaluation.py
ocf_ml_metrics/evaluation/utils.py
ocf_ml_metrics/metrics/__init__.py
ocf_ml_metrics/metrics/errors.py
ocf_ml_metrics/metrics/utils.py
tests/__init__.py
tests/consts_for_tests.py
ocf_ml_metrics-0.0.11.dist-info/LICENSE
ocf_ml_metrics-0.0.11.dist-info/METADATA
ocf_ml_metrics-0.0.11.dist-info/WHEEL
ocf_ml_metrics-0.0.11.dist-info/top_level.txt
ocf_ml_metrics-0.0.11.dist-info/RECORD
