Metadata-Version: 2.1
Name: ocf_ml_metrics
Version: 0.0.11
Summary: Common metrics and baselines for OCF's energy forecasting work
Author: Jacob Bieker, Jack Kelly, Peter Dudfield
Author-email: info@openclimatefix.org
License: MIT
License-File: LICENSE
Requires-Dist: numpy
Requires-Dist: pvlib
Requires-Dist: pandas
